{"XAy6XJVZHTzH+1dgA4IMSQ==":"logo-1400x904.png","f4Jn27BWOHJ0Yhc6pgajGg==":"logo-198x128.png","BLZQgfL0F74LTKMh2wfVyw==":"camera-275007-2000x1332.jpg","nSrrLHdB74X3vsKJd5Of8A==":"images-2000x1498.jpg","5ngNGl/l31NP0PPAlgnFcg==":"images-2000x2000.jpg","rB/F7QukzvjEzbgKHWUkFg==":"camera-2341279-2000x1268.jpg","etqrL2GSvA1dMoKJi9kBeA==":"downloadfile-2000x1332.jpg","wC8eu99ba+tIkziEWWGsOw==":"techland-1822629-2000x1290.jpg","lmtFDs4DAa1DJSpFtG8P0w==":"images-2000x1376.jpg","6cmEEhkV52Pas0djqnJTYw==":"south-africa-1036571-2000x1500.jpg","SkxRgNpL7ZVg9qWoUDDBlA==":"downloadfile-2000x1334.jpg","4TElPXfayiZQ+aevOei+8A==":"camera-801924-2000x1332.jpg","mTqDC+oc0a3c4+4TDLBt3w==":"spotlight-802633-2000x1500.jpg","YH5GX2BqPQwmDSH/AdkL/A==":"music-546063-2000x1414.png","YQMWJlHtquckJsnqi2TUgQ==":"pexels-photo-2000x1498.png","mqbvgTLPQzZbCd5Tr++yHw==":"dinner-party-1937040-2000x1331.jpg","fIuwRUZnPpjr2AQKieBEGg==":"downloadfile-2000x1500.jpg","yig8es4TFI5D/9MpIVSzvw==":"downloadfile-2000x1328.jpg","D+mAejmQydfdjmSfgIb5+A==":"spot-950389-2000x1332.jpg","Jtscw9KknuCiNzBJPPqD2w==":"downloadfile-600x396.jpg","hUDcQHl1kugWqn4ilih1GA==":"images-600x383.jpg","hOmVC18JS5k+ehI7LJE28g==":"images-600x449.jpg","inHdrAO2rEf5zf4uTe44WQ==":"images-600x450.jpg","nsH8aUmLazhEuICJga5iSw==":"images-600x412.jpg","PLwl3JyytPTn502pXs5IKQ==":"images-1-600x449.jpg","VtSYER7DVg1vrYNcBClhKg==":"images-600x389.jpg","YQPRMx8Oc6XtjmukmuxXCA==":"images-600x413.jpg","vYprkzC0twK1NxL0mLSJ3g==":"marquee-419284-600x399.jpg","JZz1nVSK9aSWGjPv4YPs1Q==":"images-600x396.jpg","3AfHEVX85v85sleXyhOShw==":"images-1-600x396.jpg","ZkWgmqUBnqhlBl12vKc/DA==":"images-600x777.jpg","eV790gbPhlHdf2b7k+DAUw==":"images-2-600x396.jpg","SV2OSm9CiwmuPWwQp+bh/A==":"images-600x409.jpg","XQXHAQ0rfVNO5Pmwspho4w==":"images-1-600x409.jpg","dzW2nqQy/WFlmEBeYyuyBw==":"wedding-reception-1967373-600x409.jpg","9rO9NSaLSZvIqdbc8PZi0w==":"images-600x600.jpg","J1Doi3xacWd4Ha3nEBRCcg==":"images-2-600x409.jpg","hRDpXvqQNCleBQHF4aolcg==":"wedding-decor-600x396.jpg","IFBjCp6EeZpeW1D+naRllA==":"stretch-tents-600x396.jpg","ZWI47Ik+r3tXtdxNQLSmyA==":"gzbmq-na-6x12m-wht-deal01-600x396.jpg","MVUJPI3XJyoiaSfSVGbbVg==":"catering-equipment-600x396.jpg","hsfghNqmzNu9S6l79kLxEA==":"wedding-rings-600x396.jpg","a+VT3Hx7+HO72vTs9AtGKQ==":"meaningful-and-wonderful-birthday-wishes-that-your-friend-will-never-forget-600x396.png","1bX2WxKo/ImDnBobnIo0wA==":"south-africa-govt-sweggs-flickr-600x396.jpg","jYt2n7cAziDu97583DeRhQ==":"wedding+sound+system+with+2xsub+-600x396.jpg","cerLBFsXbqZqffP450dBHw==":"stage-and-lighting-600x396.jpg","7D3TOsaZ7v6ZKpjX0gUEBg==":"camera-600x396.jpg","dGykdexjHJP+1B/bRbIX5w==":"video-camera-600x396.jpg","twQNBIQbCtWXnR6KJjaeQg==":"stage-and-lighting-equipment-2000x1321.jpg"}